[
    {
        "background": "sprites/bg_1.png",
        "completed": true,
        "difficulty": 1,
        "lives": 4,
        "locked": false,
        "name": "Tutorial",
        "single_animations": "animations/one_time/properties.json",
        "tilemap": "tilemaps/tutorial.tmx"
    },
    {
        "background": "sprites/bg_1.png",
        "completed": false,
        "difficulty": 2,
        "lives": 6,
        "locked": true,
        "name": "Level 1",
        "single_animations": "animations/one_time/properties.json",
        "tilemap": "tilemaps/map1.tmx"
    }
]
